udata_event_consumer/__init__.py
udata_event_consumer/commands.py
udata_event_consumer/consumer.py
udata_event_consumer/dataset/event.py
udata_event_consumer-0.1.0.dev20.dist-info/entry_points.txt
udata_event_consumer-0.1.0.dev20.dist-info/WHEEL
udata_event_consumer-0.1.0.dev20.dist-info/METADATA
udata_event_consumer-0.1.0.dev20.dist-info/RECORD
