Metadata-Version: 2.1
Name: udata-event-consumer
Version: 0.1.0.dev20
Summary: A udata plugin to consume kafka events
Author-email: Open Data Team <contact@opendata.team>
Classifier: Development Status :: 5 - Production/Stable
Classifier: Intended Audience :: Developers
Classifier: License :: OSI Approved :: MIT License
Classifier: Operating System :: OS Independent
Classifier: Programming Language :: Python
Classifier: Programming Language :: Python :: 3.9
Requires-Dist: udata>=4.0.1
Requires-Dist: udata_event_service==0.0.8
Requires-Dist: flake8==3.7.8 ; extra == "dev"
Requires-Dist: invoke==1.3.0 ; extra == "dev"
Requires-Dist: pytest-cov==2.6.1 ; extra == "dev"
Requires-Dist: flit==3.6.0 ; extra == "dev"
Requires-Dist: httpretty==0.9.7 ; extra == "test"
Requires-Dist: mock==3.0.5 ; extra == "test"
Requires-Dist: pytest-flask==0.15.0 ; extra == "test"
Requires-Dist: pytest-sugar==0.9.2 ; extra == "test"
Requires-Dist: pytest==4.6.3 ; extra == "test"
Project-URL: Home, https://github.com/etalab/udata-event-consumer
Provides-Extra: dev
Provides-Extra: test
